README.md
apidoc2.py
setup.py
apidoc2.egg-info/PKG-INFO
apidoc2.egg-info/SOURCES.txt
apidoc2.egg-info/dependency_links.txt
apidoc2.egg-info/entry_points.txt
apidoc2.egg-info/top_level.txt