Metadata-Version: 2.1
Name: apidoc2
Version: 0.1.2
Summary: 从Java项目批量提取ApiDoc注解并生成API文档的工具
Home-page: https://gitlab-code.howbuy.pa/ftx/apidoc-ext
Author: meng.lv
Author-email: meng.lv@howbuy.com
License: UNKNOWN
Platform: UNKNOWN
Classifier: Programming Language :: Python :: 3
Classifier: License :: OSI Approved :: MIT License
Classifier: Operating System :: OS Independent
Requires-Python: >=3.6
